{
"meta":{"test_sets":[],"test_metrics":[],"learn_metrics":[{"best_value":"Min","name":"RMSE"}],"launch_mode":"Train","parameters":"","iteration_count":263,"learn_sets":["learn"],"name":"experiment"},
"iterations":[
{"learn":[0.754071076],"iteration":0,"passed_time":0.004759873554,"remaining_time":1.247086871},
{"learn":[0.7473958904],"iteration":1,"passed_time":0.008425916041,"remaining_time":1.099582043},
{"learn":[0.7403473344],"iteration":2,"passed_time":0.01199332384,"remaining_time":1.0394214},
{"learn":[0.7332942406],"iteration":3,"passed_time":0.01549760504,"remaining_time":1.003469926},
{"learn":[0.7272325558],"iteration":4,"passed_time":0.0190416741,"remaining_time":0.9825503836},
{"learn":[0.7202928414],"iteration":5,"passed_time":0.02268799765,"remaining_time":0.971802566},
{"learn":[0.714589736],"iteration":6,"passed_time":0.02626411498,"remaining_time":0.960516205},
{"learn":[0.7107458258],"iteration":7,"passed_time":0.03024460052,"remaining_time":0.9640466417},
{"learn":[0.7045995283],"iteration":8,"passed_time":0.03378430982,"remaining_time":0.9534682993},
{"learn":[0.6998580788],"iteration":9,"passed_time":0.03721487499,"remaining_time":0.9415363373},
{"learn":[0.6954041625],"iteration":10,"passed_time":0.04085761373,"remaining_time":0.9360107873},
{"learn":[0.6908199487],"iteration":11,"passed_time":0.0443551153,"remaining_time":0.9277611617},
{"learn":[0.6863492756],"iteration":12,"passed_time":0.04780228958,"remaining_time":0.9192747996},
{"learn":[0.6831911569],"iteration":13,"passed_time":0.0511836574,"remaining_time":0.9103379066},
{"learn":[0.6794872321],"iteration":14,"passed_time":0.05470922745,"remaining_time":0.9045258939},
{"learn":[0.6757232205],"iteration":15,"passed_time":0.05826497088,"remaining_time":0.899465488},
{"learn":[0.6718353871],"iteration":16,"passed_time":0.06162930962,"remaining_time":0.8918123628},
{"learn":[0.6687481068],"iteration":17,"passed_time":0.06498690873,"remaining_time":0.8845440355},
{"learn":[0.6657173785],"iteration":18,"passed_time":0.06838913543,"remaining_time":0.878260476},
{"learn":[0.662909839],"iteration":19,"passed_time":0.07181914063,"remaining_time":0.8726025587},
{"learn":[0.6601601949],"iteration":20,"passed_time":0.07524018632,"remaining_time":0.8670535757},
{"learn":[0.6563041527],"iteration":21,"passed_time":0.07854968801,"remaining_time":0.8604761278},
{"learn":[0.6535850038],"iteration":22,"passed_time":0.0819299159,"remaining_time":0.8549208615},
{"learn":[0.6504827359],"iteration":23,"passed_time":0.08528358521,"remaining_time":0.8492823694},
{"learn":[0.6479628579],"iteration":24,"passed_time":0.08889360072,"remaining_time":0.8462670788},
{"learn":[0.6453081433],"iteration":25,"passed_time":0.09233252544,"remaining_time":0.8416464819},
{"learn":[0.6422941153],"iteration":26,"passed_time":0.09573282224,"remaining_time":0.8367757796},
{"learn":[0.6398395756],"iteration":27,"passed_time":0.09919722559,"remaining_time":0.8325481434},
{"learn":[0.636862653],"iteration":28,"passed_time":0.1025198666,"remaining_time":0.8272292683},
{"learn":[0.634231176],"iteration":29,"passed_time":0.1060416268,"remaining_time":0.8235899685},
{"learn":[0.6319715038],"iteration":30,"passed_time":0.1094228547,"remaining_time":0.8189065253},
{"learn":[0.6294156042],"iteration":31,"passed_time":0.1127238268,"remaining_time":0.8137251249},
{"learn":[0.6275030694],"iteration":32,"passed_time":0.116154492,"remaining_time":0.8095616109},
{"learn":[0.6259882622],"iteration":33,"passed_time":0.1197206949,"remaining_time":0.8063540919},
{"learn":[0.6240297648],"iteration":34,"passed_time":0.1230850236,"remaining_time":0.8018110109},
{"learn":[0.6218769926],"iteration":35,"passed_time":0.1264470025,"remaining_time":0.7973185989},
{"learn":[0.6195511346],"iteration":36,"passed_time":0.1298835073,"remaining_time":0.7933425042},
{"learn":[0.6175105889],"iteration":37,"passed_time":0.1332522358,"remaining_time":0.7889935016},
{"learn":[0.6158036486],"iteration":38,"passed_time":0.1367058448,"remaining_time":0.7851822878},
{"learn":[0.6141626248],"iteration":39,"passed_time":0.1400508845,"remaining_time":0.7807836813},
{"learn":[0.6124182143],"iteration":40,"passed_time":0.1434182931,"remaining_time":0.7765575871},
{"learn":[0.6103845977],"iteration":41,"passed_time":0.1468880262,"remaining_time":0.7729108044},
{"learn":[0.6085451394],"iteration":42,"passed_time":0.1504036068,"remaining_time":0.7695068253},
{"learn":[0.6075067188],"iteration":43,"passed_time":0.1540911881,"remaining_time":0.766953868},
{"learn":[0.6061229649],"iteration":44,"passed_time":0.1577879189,"remaining_time":0.7643948073},
{"learn":[0.6047261577],"iteration":45,"passed_time":0.1614861197,"remaining_time":0.7617932168},
{"learn":[0.6035956314],"iteration":46,"passed_time":0.1650640469,"remaining_time":0.7585922156},
{"learn":[0.6023505939],"iteration":47,"passed_time":0.1685198407,"remaining_time":0.7548284533},
{"learn":[0.6013208505],"iteration":48,"passed_time":0.1720914483,"remaining_time":0.7515830599},
{"learn":[0.5998619624],"iteration":49,"passed_time":0.1754453076,"remaining_time":0.7473970104},
{"learn":[0.5980784483],"iteration":50,"passed_time":0.1787443999,"remaining_time":0.7430159367},
{"learn":[0.5969544012],"iteration":51,"passed_time":0.182230782,"remaining_time":0.7394364425},
{"learn":[0.5956816257],"iteration":52,"passed_time":0.1857320134,"remaining_time":0.7359192984},
{"learn":[0.5945661753],"iteration":53,"passed_time":0.1891153811,"remaining_time":0.7319465676},
{"learn":[0.59342835],"iteration":54,"passed_time":0.1924265427,"remaining_time":0.7277221979},
{"learn":[0.5920092035],"iteration":55,"passed_time":0.1958773382,"remaining_time":0.7240465894},
{"learn":[0.5906941005],"iteration":56,"passed_time":0.199202749,"remaining_time":0.7199257246},
{"learn":[0.5895756191],"iteration":57,"passed_time":0.2027004792,"remaining_time":0.7164413489},
{"learn":[0.5885167404],"iteration":58,"passed_time":0.2060903066,"remaining_time":0.7125834329},
{"learn":[0.5870193649],"iteration":59,"passed_time":0.2094714444,"remaining_time":0.7087117202},
{"learn":[0.5855656899],"iteration":60,"passed_time":0.2128616117,"remaining_time":0.704885993},
{"learn":[0.5841926394],"iteration":61,"passed_time":0.2163326547,"remaining_time":0.7013365097},
{"learn":[0.5833588097],"iteration":62,"passed_time":0.219891413,"remaining_time":0.6980679778},
{"learn":[0.5819860851],"iteration":63,"passed_time":0.223250272,"remaining_time":0.6941688146},
{"learn":[0.5806619415],"iteration":64,"passed_time":0.2267208051,"remaining_time":0.6906264523},
{"learn":[0.5791811762],"iteration":65,"passed_time":0.2301423307,"remaining_time":0.6869399872},
{"learn":[0.5782474664],"iteration":66,"passed_time":0.2335000598,"remaining_time":0.6830748019},
{"learn":[0.5769130293],"iteration":67,"passed_time":0.2369215355,"remaining_time":0.6794073444},
{"learn":[0.5762333588],"iteration":68,"passed_time":0.2402114382,"remaining_time":0.6753770872},
{"learn":[0.5750997511],"iteration":69,"passed_time":0.2435414888,"remaining_time":0.6714786763},
{"learn":[0.5734054809],"iteration":70,"passed_time":0.2469109973,"remaining_time":0.6677029786},
{"learn":[0.5726751156],"iteration":71,"passed_time":0.2502657079,"remaining_time":0.6638993085},
{"learn":[0.5715141849],"iteration":72,"passed_time":0.2536945118,"remaining_time":0.6603007842},
{"learn":[0.5703660714],"iteration":73,"passed_time":0.2570715899,"remaining_time":0.6565747363},
{"learn":[0.5692287746],"iteration":74,"passed_time":0.2604435782,"remaining_time":0.652845236},
{"learn":[0.5674475586],"iteration":75,"passed_time":0.2637365608,"remaining_time":0.6489307482},
{"learn":[0.5662097537],"iteration":76,"passed_time":0.2670809456,"remaining_time":0.6451565699},
{"learn":[0.5650164497],"iteration":77,"passed_time":0.2704858822,"remaining_time":0.6415370282},
{"learn":[0.563859358],"iteration":78,"passed_time":0.2738432613,"remaining_time":0.6378121528},
{"learn":[0.5621590316],"iteration":79,"passed_time":0.2772340486,"remaining_time":0.6341728861},
{"learn":[0.5609569916],"iteration":80,"passed_time":0.280679143,"remaining_time":0.630661778},
{"learn":[0.5596569698],"iteration":81,"passed_time":0.2840579559,"remaining_time":0.6270059759},
{"learn":[0.5579894027],"iteration":82,"passed_time":0.2873948362,"remaining_time":0.6232659097},
{"learn":[0.5568407454],"iteration":83,"passed_time":0.2908256613,"remaining_time":0.6197356354},
{"learn":[0.555688094],"iteration":84,"passed_time":0.2941229137,"remaining_time":0.6159279839},
{"learn":[0.5545061569],"iteration":85,"passed_time":0.2973844979,"remaining_time":0.6120587923},
{"learn":[0.5533149019],"iteration":86,"passed_time":0.3007545364,"remaining_time":0.6084229701},
{"learn":[0.5522164763],"iteration":87,"passed_time":0.3041600629,"remaining_time":0.6048637615},
{"learn":[0.5513733024],"iteration":88,"passed_time":0.3075070026,"remaining_time":0.6011934657},
{"learn":[0.5498969558],"iteration":89,"passed_time":0.3108574221,"remaining_time":0.5975370446},
{"learn":[0.5490456107],"iteration":90,"passed_time":0.3141312757,"remaining_time":0.593742631},
{"learn":[0.5479203698],"iteration":91,"passed_time":0.3176392967,"remaining_time":0.5903947797},
{"learn":[0.5470148028],"iteration":92,"passed_time":0.3209407788,"remaining_time":0.5866659398},
{"learn":[0.5462332129],"iteration":93,"passed_time":0.3242236019,"remaining_time":0.5829126461},
{"learn":[0.5449634681],"iteration":94,"passed_time":0.3275859208,"remaining_time":0.5793098389},
{"learn":[0.5440610643],"iteration":95,"passed_time":0.3309169113,"remaining_time":0.5756575437},
{"learn":[0.5432941105],"iteration":96,"passed_time":0.3345200072,"remaining_time":0.5724775381},
{"learn":[0.5419769422],"iteration":97,"passed_time":0.3378713067,"remaining_time":0.5688649551},
{"learn":[0.5415292569],"iteration":98,"passed_time":0.341224696,"remaining_time":0.5652611125},
{"learn":[0.5408064042],"iteration":99,"passed_time":0.344584495,"remaining_time":0.5616727268},
{"learn":[0.5396885287],"iteration":100,"passed_time":0.3479369894,"remaining_time":0.5580771512},
{"learn":[0.5384902507],"iteration":101,"passed_time":0.3514047725,"remaining_time":0.5546683174},
{"learn":[0.5378564769],"iteration":102,"passed_time":0.3546842058,"remaining_time":0.5509657566},
{"learn":[0.5366136088],"iteration":103,"passed_time":0.3579707088,"remaining_time":0.5472821413},
{"learn":[0.5359146062],"iteration":104,"passed_time":0.361326748,"remaining_time":0.5437107255},
{"learn":[0.5353609687],"iteration":105,"passed_time":0.3647355643,"remaining_time":0.5402215434},
{"learn":[0.5343622772],"iteration":106,"passed_time":0.3680916735,"remaining_time":0.5366570193},
{"learn":[0.5333196048],"iteration":107,"passed_time":0.3714069149,"remaining_time":0.5330377019},
{"learn":[0.5323724378],"iteration":108,"passed_time":0.3746920879,"remaining_time":0.529381482},
{"learn":[0.531537887],"iteration":109,"passed_time":0.3780928147,"remaining_time":0.5258927331},
{"learn":[0.5304786818],"iteration":110,"passed_time":0.3815708273,"remaining_time":0.5225114031},
{"learn":[0.5297423588],"iteration":111,"passed_time":0.3849570248,"remaining_time":0.5190045603},
{"learn":[0.5288771219],"iteration":112,"passed_time":0.3882541972,"remaining_time":0.5153816777},
{"learn":[0.5281833571],"iteration":113,"passed_time":0.3916376049,"remaining_time":0.5118772205},
{"learn":[0.5273225942],"iteration":114,"passed_time":0.3949837246,"remaining_time":0.5083268804},
{"learn":[0.526553049],"iteration":115,"passed_time":0.3984145298,"remaining_time":0.5048873783},
{"learn":[0.5257329801],"iteration":116,"passed_time":0.401825951,"remaining_time":0.5014238363},
{"learn":[0.5247711486],"iteration":117,"passed_time":0.4052830547,"remaining_time":0.498017313},
{"learn":[0.5237341077],"iteration":118,"passed_time":0.4087163698,"remaining_time":0.4945811533},
{"learn":[0.5226538864],"iteration":119,"passed_time":0.4122925821,"remaining_time":0.491315327},
{"learn":[0.5220287321],"iteration":120,"passed_time":0.4159060174,"remaining_time":0.4880880535},
{"learn":[0.5214756579],"iteration":121,"passed_time":0.4191774912,"remaining_time":0.4844592316},
{"learn":[0.5206106322],"iteration":122,"passed_time":0.4224360056,"remaining_time":0.4808214698},
{"learn":[0.5195963967],"iteration":123,"passed_time":0.4258761903,"remaining_time":0.4773934713},
{"learn":[0.5184693942],"iteration":124,"passed_time":0.4291802222,"remaining_time":0.4738149654},
{"learn":[0.5175940588],"iteration":125,"passed_time":0.4327915691,"remaining_time":0.47057496},
{"learn":[0.5163537803],"iteration":126,"passed_time":0.4361738768,"remaining_time":0.4670838366},
{"learn":[0.5153997354],"iteration":127,"passed_time":0.4395598144,"remaining_time":0.4635982418},
{"learn":[0.5148543927],"iteration":128,"passed_time":0.4429150736,"remaining_time":0.4600823246},
{"learn":[0.5134042567],"iteration":129,"passed_time":0.4462779511,"remaining_time":0.456576673},
{"learn":[0.5121400203],"iteration":130,"passed_time":0.449712481,"remaining_time":0.4531454007},
{"learn":[0.5111477439],"iteration":131,"passed_time":0.4530756898,"remaining_time":0.4496432982},
{"learn":[0.510145238],"iteration":132,"passed_time":0.4565396132,"remaining_time":0.4462417272},
{"learn":[0.5090649465],"iteration":133,"passed_time":0.4600258304,"remaining_time":0.4428606875},
{"learn":[0.5085513892],"iteration":134,"passed_time":0.4634929236,"remaining_time":0.4394599572},
{"learn":[0.5073536355],"iteration":135,"passed_time":0.4668645619,"remaining_time":0.435969113},
{"learn":[0.5066913224],"iteration":136,"passed_time":0.4701461651,"remaining_time":0.432397203},
{"learn":[0.5057866646],"iteration":137,"passed_time":0.4734494272,"remaining_time":0.4288491188},
{"learn":[0.5050547739],"iteration":138,"passed_time":0.4771202794,"remaining_time":0.4256324795},
{"learn":[0.5037460376],"iteration":139,"passed_time":0.4806748379,"remaining_time":0.422307179},
{"learn":[0.5022871591],"iteration":140,"passed_time":0.4840847042,"remaining_time":0.418853432},
{"learn":[0.5015972455],"iteration":141,"passed_time":0.4873336391,"remaining_time":0.4152631714},
{"learn":[0.5007198019],"iteration":142,"passed_time":0.4908605841,"remaining_time":0.4119109797},
{"learn":[0.4997207462],"iteration":143,"passed_time":0.4942363272,"remaining_time":0.4084314093},
{"learn":[0.4991613536],"iteration":144,"passed_time":0.4977751966,"remaining_time":0.405086022},
{"learn":[0.4982743704],"iteration":145,"passed_time":0.501202112,"remaining_time":0.4016482678},
{"learn":[0.4973535038],"iteration":146,"passed_time":0.5045551413,"remaining_time":0.3981523564},
{"learn":[0.4959707661],"iteration":147,"passed_time":0.5079736171,"remaining_time":0.3947092295},
{"learn":[0.4951661181],"iteration":148,"passed_time":0.5114813181,"remaining_time":0.3913346998},
{"learn":[0.4944380583],"iteration":149,"passed_time":0.514861786,"remaining_time":0.3878625455},
{"learn":[0.4935505513],"iteration":150,"passed_time":0.5183274593,"remaining_time":0.3844548042},
{"learn":[0.4927446853],"iteration":151,"passed_time":0.5217468351,"remaining_time":0.3810124914},
{"learn":[0.4913860235],"iteration":152,"passed_time":0.5250622265,"remaining_time":0.3774957184},
{"learn":[0.4907647433],"iteration":153,"passed_time":0.5286092953,"remaining_time":0.3741455402},
{"learn":[0.4899871264],"iteration":154,"passed_time":0.5319028179,"remaining_time":0.370616157},
{"learn":[0.489286002],"iteration":155,"passed_time":0.5353483923,"remaining_time":0.3671940896},
{"learn":[0.488467071],"iteration":156,"passed_time":0.5387522689,"remaining_time":0.3637435701},
{"learn":[0.4879727867],"iteration":157,"passed_time":0.5421066582,"remaining_time":0.3602607538},
{"learn":[0.4870767734],"iteration":158,"passed_time":0.5455828009,"remaining_time":0.3568591905},
{"learn":[0.4857859758],"iteration":159,"passed_time":0.5489232009,"remaining_time":0.3533693106},
{"learn":[0.4853145369],"iteration":160,"passed_time":0.55230741,"remaining_time":0.3499090423},
{"learn":[0.484654971],"iteration":161,"passed_time":0.5556825381,"remaining_time":0.3464440515},
{"learn":[0.4829282341],"iteration":162,"passed_time":0.5590678757,"remaining_time":0.3429864268},
{"learn":[0.482340674],"iteration":163,"passed_time":0.5625011394,"remaining_time":0.3395586146},
{"learn":[0.4814512591],"iteration":164,"passed_time":0.565904756,"remaining_time":0.3361131278},
{"learn":[0.4807558149],"iteration":165,"passed_time":0.5692112979,"remaining_time":0.332611421},
{"learn":[0.4798715031],"iteration":166,"passed_time":0.5725941156,"remaining_time":0.3291558988},
{"learn":[0.4792519506],"iteration":167,"passed_time":0.5759739635,"remaining_time":0.3256995627},
{"learn":[0.4782994623],"iteration":168,"passed_time":0.5794329571,"remaining_time":0.3222881537},
{"learn":[0.4770366308],"iteration":169,"passed_time":0.5828679021,"remaining_time":0.3188630288},
{"learn":[0.475526768],"iteration":170,"passed_time":0.586228871,"remaining_time":0.3153979891},
{"learn":[0.4749982241],"iteration":171,"passed_time":0.5895094943,"remaining_time":0.311891651},
{"learn":[0.4743864057],"iteration":172,"passed_time":0.5929538187,"remaining_time":0.3084730849},
{"learn":[0.4734037086],"iteration":173,"passed_time":0.596382544,"remaining_time":0.3050462437},
{"learn":[0.4724112808],"iteration":174,"passed_time":0.5998097993,"remaining_time":0.3016186419},
{"learn":[0.4714239424],"iteration":175,"passed_time":0.6030615141,"remaining_time":0.2981042712},
{"learn":[0.469913027],"iteration":176,"passed_time":0.6064438219,"remaining_time":0.2946563202},
{"learn":[0.4691966234],"iteration":177,"passed_time":0.6099145663,"remaining_time":0.2912513378},
{"learn":[0.4682160612],"iteration":178,"passed_time":0.613365799,"remaining_time":0.2878364643},
{"learn":[0.467631394],"iteration":179,"passed_time":0.6170555402,"remaining_time":0.2845311657},
{"learn":[0.4665634189],"iteration":180,"passed_time":0.6206634558,"remaining_time":0.281184549},
{"learn":[0.4652434132],"iteration":181,"passed_time":0.6243946762,"remaining_time":0.2778899383},
{"learn":[0.4645940807],"iteration":182,"passed_time":0.6281999897,"remaining_time":0.2746229463},
{"learn":[0.463528512],"iteration":183,"passed_time":0.6322740902,"remaining_time":0.2714655061},
{"learn":[0.4623794246],"iteration":184,"passed_time":0.6361876194,"remaining_time":0.2682304557},
{"learn":[0.4614163608],"iteration":185,"passed_time":0.6401462761,"remaining_time":0.2650067917},
{"learn":[0.4607553608],"iteration":186,"passed_time":0.6442556347,"remaining_time":0.2618365146},
{"learn":[0.4595579958],"iteration":187,"passed_time":0.6481866829,"remaining_time":0.2585851129},
{"learn":[0.4590095243],"iteration":188,"passed_time":0.6519474403,"remaining_time":0.2552598444},
{"learn":[0.4581476627],"iteration":189,"passed_time":0.6557510868,"remaining_time":0.2519464702},
{"learn":[0.4575594686],"iteration":190,"passed_time":0.6601699187,"remaining_time":0.2488598646},
{"learn":[0.4560949971],"iteration":191,"passed_time":0.6644122788,"remaining_time":0.2456941239},
{"learn":[0.4552469994],"iteration":192,"passed_time":0.668176376,"remaining_time":0.2423437633},
{"learn":[0.4547409003],"iteration":193,"passed_time":0.6718376137,"remaining_time":0.2389525533},
{"learn":[0.4538300475],"iteration":194,"passed_time":0.6752562845,"remaining_time":0.2354739864},
{"learn":[0.4528332439],"iteration":195,"passed_time":0.6785796855,"remaining_time":0.2319634639},
{"learn":[0.4521728431],"iteration":196,"passed_time":0.681911026,"remaining_time":0.2284575011},
{"learn":[0.4514145344],"iteration":197,"passed_time":0.6852820244,"remaining_time":0.2249663211},
{"learn":[0.4507707241],"iteration":198,"passed_time":0.6885780268,"remaining_time":0.2214522297},
{"learn":[0.4501049801],"iteration":199,"passed_time":0.6919162969,"remaining_time":0.2179536335},
{"learn":[0.4492321906],"iteration":200,"passed_time":0.6953258832,"remaining_time":0.2144786306},
{"learn":[0.4484823993],"iteration":201,"passed_time":0.6987161206,"remaining_time":0.2109984325},
{"learn":[0.4476045103],"iteration":202,"passed_time":0.7021273768,"remaining_time":0.207525333},
{"learn":[0.4466476338],"iteration":203,"passed_time":0.7054945354,"remaining_time":0.2040400862},
{"learn":[0.4461814551],"iteration":204,"passed_time":0.7089277304,"remaining_time":0.2005746749},
{"learn":[0.4456394362],"iteration":205,"passed_time":0.7124494207,"remaining_time":0.197134063},
{"learn":[0.4444427272],"iteration":206,"passed_time":0.7158441278,"remaining_time":0.1936583148},
{"learn":[0.4434535394],"iteration":207,"passed_time":0.7193074912,"remaining_time":0.1902015001},
{"learn":[0.4427227862],"iteration":208,"passed_time":0.7227172475,"remaining_time":0.1867307721},
{"learn":[0.4420684891],"iteration":209,"passed_time":0.726178971,"remaining_time":0.1832737403},
{"learn":[0.4414438967],"iteration":210,"passed_time":0.7296141459,"remaining_time":0.1798101213},
{"learn":[0.4411655907],"iteration":211,"passed_time":0.73306451,"remaining_time":0.1763504246},
{"learn":[0.4407974666],"iteration":212,"passed_time":0.7364590071,"remaining_time":0.1728777012},
{"learn":[0.4396694931],"iteration":213,"passed_time":0.7399123411,"remaining_time":0.1694191809},
{"learn":[0.4389453645],"iteration":214,"passed_time":0.74327252,"remaining_time":0.1659399114},
{"learn":[0.4379915],"iteration":215,"passed_time":0.7467591422,"remaining_time":0.1624892578},
{"learn":[0.4373276152],"iteration":216,"passed_time":0.7502506791,"remaining_time":0.1590393145},
{"learn":[0.4358618596],"iteration":217,"passed_time":0.753648426,"remaining_time":0.1555696292},
{"learn":[0.4349280011],"iteration":218,"passed_time":0.757120279,"remaining_time":0.1521154898},
{"learn":[0.4343010513],"iteration":219,"passed_time":0.7604638388,"remaining_time":0.148636114},
{"learn":[0.4334486126],"iteration":220,"passed_time":0.7639729498,"remaining_time":0.1451894294},
{"learn":[0.4325599504],"iteration":221,"passed_time":0.7674228939,"remaining_time":0.1417312552},
{"learn":[0.4318323208],"iteration":222,"passed_time":0.770706517,"remaining_time":0.1382433214},
{"learn":[0.4309449822],"iteration":223,"passed_time":0.7742356568,"remaining_time":0.1347999581},
{"learn":[0.4303806916],"iteration":224,"passed_time":0.7776529827,"remaining_time":0.1313369482},
{"learn":[0.4297542496],"iteration":225,"passed_time":0.78104416,"remaining_time":0.1278700616},
{"learn":[0.4291106797],"iteration":226,"passed_time":0.7843711008,"remaining_time":0.1243936547},
{"learn":[0.4282377177],"iteration":227,"passed_time":0.787762788,"remaining_time":0.1209284982},
{"learn":[0.4274563431],"iteration":228,"passed_time":0.7912443105,"remaining_time":0.1174773212},
{"learn":[0.4270418062],"iteration":229,"passed_time":0.794669026,"remaining_time":0.1140177298},
{"learn":[0.4265454844],"iteration":230,"passed_time":0.7980003865,"remaining_time":0.1105455081},
{"learn":[0.426135372],"iteration":231,"passed_time":0.8012883293,"remaining_time":0.1070686992},
{"learn":[0.4250245268],"iteration":232,"passed_time":0.8046508982,"remaining_time":0.1036031199},
{"learn":[0.4242387449],"iteration":233,"passed_time":0.8082189759,"remaining_time":0.1001638902},
{"learn":[0.4236497967],"iteration":234,"passed_time":0.8117785542,"remaining_time":0.09672255113},
{"learn":[0.4228347497],"iteration":235,"passed_time":0.8151375332,"remaining_time":0.09325726015},
{"learn":[0.4221853776],"iteration":236,"passed_time":0.8185078116,"remaining_time":0.08979410592},
{"learn":[0.4208689942],"iteration":237,"passed_time":0.8220221673,"remaining_time":0.08634686631},
{"learn":[0.4199494795],"iteration":238,"passed_time":0.8255294983,"remaining_time":0.08289835966},
{"learn":[0.4189725167],"iteration":239,"passed_time":0.8288264207,"remaining_time":0.07942919865},
{"learn":[0.4182780288],"iteration":240,"passed_time":0.8321750803,"remaining_time":0.0759661899},
{"learn":[0.417724793],"iteration":241,"passed_time":0.8354177156,"remaining_time":0.07249492573},
{"learn":[0.4169723842],"iteration":242,"passed_time":0.8388705145,"remaining_time":0.0690428407},
{"learn":[0.416445569],"iteration":243,"passed_time":0.8422625318,"remaining_time":0.06558601682},
{"learn":[0.4154644302],"iteration":244,"passed_time":0.8457383745,"remaining_time":0.06213588058},
{"learn":[0.4145820875],"iteration":245,"passed_time":0.8491366114,"remaining_time":0.05868017234},
{"learn":[0.4139299249],"iteration":246,"passed_time":0.8524888008,"remaining_time":0.05522194661},
{"learn":[0.4127248853],"iteration":247,"passed_time":0.8560549087,"remaining_time":0.05177751464},
{"learn":[0.4119475272],"iteration":248,"passed_time":0.8594263671,"remaining_time":0.0483211612},
{"learn":[0.4113392342],"iteration":249,"passed_time":0.8628577322,"remaining_time":0.04486860207},
{"learn":[0.410581242],"iteration":250,"passed_time":0.8662508394,"remaining_time":0.04141438276},
{"learn":[0.4101567237],"iteration":251,"passed_time":0.8695938193,"remaining_time":0.03795846037},
{"learn":[0.4095599351],"iteration":252,"passed_time":0.8731031002,"remaining_time":0.03451000396},
{"learn":[0.4088151778],"iteration":253,"passed_time":0.8764573095,"remaining_time":0.03105557396},
{"learn":[0.4081487765],"iteration":254,"passed_time":0.8798246681,"remaining_time":0.02760234253},
{"learn":[0.4075361005],"iteration":255,"passed_time":0.8831888418,"remaining_time":0.02414969489},
{"learn":[0.4068612159],"iteration":256,"passed_time":0.886694248,"remaining_time":0.02070103303},
{"learn":[0.4058197176],"iteration":257,"passed_time":0.8901098639,"remaining_time":0.01725019116},
{"learn":[0.4050562775],"iteration":258,"passed_time":0.8935572082,"remaining_time":0.01380011132},
{"learn":[0.4042407004],"iteration":259,"passed_time":0.8968224523,"remaining_time":0.01034795137},
{"learn":[0.4033794093],"iteration":260,"passed_time":0.9002040701,"remaining_time":0.00689811548},
{"learn":[0.4024163259],"iteration":261,"passed_time":0.9036240158,"remaining_time":0.003448946625},
{"learn":[0.4014837082],"iteration":262,"passed_time":0.906980335,"remaining_time":0}
]}